elegant/__init__.py
elegant/admin.py
elegant/apps.py
elegant/cache.py
elegant/compat.py
elegant/components.py
elegant/config.py
elegant/constants.py
elegant/context_processors.py
elegant/contrib/audit/__init__.py
elegant/contrib/audit/admin.py
elegant/contrib/audit/admin_helpers.py
elegant/contrib/audit/apps.py
elegant/contrib/audit/backends.py
elegant/contrib/audit/crudhistory_admin_mixin.py
elegant/contrib/audit/middleware/__init__.py
elegant/contrib/audit/middleware/audit.py
elegant/contrib/audit/migrations/__init__.py
elegant/contrib/audit/models.py
elegant/contrib/audit/settings.py
elegant/contrib/audit/signals/__init__.py
elegant/contrib/audit/signals/auth_signals.py
elegant/contrib/audit/signals/model_signals.py
elegant/contrib/audit/signals/request_signals.py
elegant/contrib/audit/templates/admin/audit/change_list.html
elegant/contrib/audit/templates/admin/audit/purge_confirmation.html
elegant/contrib/audit/utils.py
elegant/locale/zh_Hans/LC_MESSAGES/django.po
elegant/mixins/__init__.py
elegant/mixins/actions.py
elegant/mixins/confirm.py
elegant/mixins/objects.py
elegant/static/elegant/bootstrap/css/bootstrap.min.css
elegant/static/elegant/bootstrap/img/glyphicons-halflings-white-shadow.png
elegant/static/elegant/bootstrap/img/glyphicons-halflings-white.png
elegant/static/elegant/bootstrap/img/glyphicons-halflings.png
elegant/static/elegant/bootstrap/js/bootstrap.min.js
elegant/static/elegant/css/confirmation.css
elegant/static/elegant/css/dashboard.css
elegant/static/elegant/css/date_range_filter.css
elegant/static/elegant/css/djangocms.css
elegant/static/elegant/css/elegant.css
elegant/static/elegant/css/extra.css
elegant/static/elegant/css/filer.css
elegant/static/elegant/css/forms.css
elegant/static/elegant/css/jquery.dropdown.min.css
elegant/static/elegant/css/shortcuts.css
elegant/static/elegant/img/ajax-loader.gif
elegant/static/elegant/img/bg_left_white.gif
elegant/static/elegant/img/bg_pattern.jpg
elegant/static/elegant/img/cc_active_nav.png
elegant_django-0.2.8.dist-info/LICENSE
elegant_django-0.2.8.dist-info/METADATA
elegant_django-0.2.8.dist-info/WHEEL
elegant_django-0.2.8.dist-info/RECORD
